libbitcoin/__init__.py
python_libbitcoin-1.2.5.dist-info/DESCRIPTION.rst
python_libbitcoin-1.2.5.dist-info/METADATA
python_libbitcoin-1.2.5.dist-info/RECORD
python_libbitcoin-1.2.5.dist-info/WHEEL
python_libbitcoin-1.2.5.dist-info/metadata.json
python_libbitcoin-1.2.5.dist-info/top_level.txt
